[
    {
        "nome": "Saul_Kripke",
        "categorias": [
            "Epistemology",
            "Metaphysics",
            "Ethics",
            "Logic",
            "Aesthetics"
        ],
        "nascimento": 1940,
        "morte": 2022
    },
    {
        "nome": "David_Lewis",
        "categorias": [
            "Epistemology",
            "Metaphysics",
            "Ethics",
            "Logic",
            "Aesthetics"
        ],
        "nascimento": 1941,
        "morte": 2001
    },
    {
        "nome": "G._E._Moore",
        "categorias": [
            "Epistemology",
            "Metaphysics",
            "Ethics",
            "Logic"
        ],
        "nascimento": 1873,
        "morte": 1958
    },
    {
        "nome": "Karl_Popper",
        "categorias": [
            "Epistemology",
            "Metaphysics",
            "Ethics",
            "Logic",
            "Politics"
        ],
        "nascimento": 1902,
        "morte": 1994
    },
    {
        "nome": "W._V._O._Quine",
        "categorias": [
            "Epistemology",
            "Metaphysics",
            "Ethics",
            "Logic"
        ],
        "nascimento": 1908,
        "morte": 2000
    },
    {
        "nome": "Bertrand_Russell",
        "categorias": [
            "Epistemology",
            "Metaphysics",
            "Ethics",
            "Logic",
            "Politics",
            "Aesthetics"
        ],
        "nascimento": 1872,
        "morte": 1970
    },
    {
        "nome": "Aristotle",
        "categorias": [
            "Epistemology",
            "Metaphysics",
            "Ethics",
            "Logic",
            "Politics",
            "Aesthetics"
        ],
        "nascimento": -384,
        "morte": -322
    },
    {
        "nome": "Adam_Smith",
        "categorias": [
            "Metaphysics",
            "Ethics",
            "Logic",
            "Politics"
        ],
        "nascimento": 1723,
        "morte": 1790
    },
    {
        "nome": "John_Maynard_Keynes",
        "categorias": [],
        "nascimento": 1883,
        "morte": 1946
    },
    {
        "nome": "David_Ricardo",
        "categorias": [],
        "nascimento": 1772,
        "morte": 1823
    },
    {
        "nome": "Vladimir_Lenin",
        "categorias": [],
        "nascimento": 1870,
        "morte": 1924
    },
    {
        "nome": "Karl_Marx",
        "categorias": [
            "Metaphysics",
            "Ethics",
            "Logic",
            "Politics",
            "Aesthetics"
        ],
        "nascimento": 1818,
        "morte": 1883
    },
    {
        "nome": "Gilles_Deleuze",
        "categorias": [
            "Epistemology",
            "Metaphysics",
            "Ethics",
            "Logic",
            "Politics",
            "Aesthetics"
        ],
        "nascimento": 1925,
        "morte": 1995
    },
    {
        "nome": "Jacques_Derrida",
        "categorias": [],
        "nascimento": 1930,
        "morte": 2004
    },
    {
        "nome": "Michel_Foucault",
        "categorias": [
            "Epistemology",
            "Metaphysics",
            "Ethics",
            "Politics",
            "Aesthetics"
        ],
        "nascimento": 1926,
        "morte": 1984
    },
    {
        "nome": "George_Berkeley",
        "categorias": [
            "Epistemology",
            "Metaphysics",
            "Ethics",
            "Politics"
        ],
        "nascimento": 1685,
        "morte": 1753
    },
    {
        "nome": "David_Hume",
        "categorias": [
            "Epistemology",
            "Metaphysics",
            "Ethics",
            "Logic",
            "Politics",
            "Aesthetics"
        ],
        "nascimento": 1711,
        "morte": 1776
    },
    {
        "nome": "John_Locke",
        "categorias": [
            "Epistemology",
            "Metaphysics",
            "Ethics",
            "Politics"
        ],
        "nascimento": 1632,
        "morte": 1704
    },
    {
        "nome": "Johann_Gottlieb_Fichte",
        "categorias": [
            "Metaphysics",
            "Ethics",
            "Politics"
        ],
        "nascimento": 1762,
        "morte": 1814
    },
    {
        "nome": "Georg_Wilhelm_Friedrich_Hegel",
        "categorias": [
            "Epistemology",
            "Metaphysics",
            "Ethics",
            "Logic",
            "Politics",
            "Aesthetics"
        ],
        "nascimento": 1770,
        "morte": 1831
    },
    {
        "nome": "Immanuel_Kant",
        "categorias": [
            "Epistemology",
            "Metaphysics",
            "Ethics",
            "Logic",
            "Politics",
            "Aesthetics"
        ],
        "nascimento": 1724,
        "morte": 1804
    },
    {
        "nome": "Martin_Heidegger",
        "categorias": [
            "Epistemology",
            "Metaphysics",
            "Ethics",
            "Logic",
            "Politics",
            "Aesthetics"
        ],
        "nascimento": 1889,
        "morte": 1976
    },
    {
        "nome": "Edmund_Husserl",
        "categorias": [
            "Epistemology",
            "Metaphysics",
            "Ethics",
            "Logic"
        ],
        "nascimento": 1859,
        "morte": 1938
    },
    {
        "nome": "Maurice_Merleau-Ponty",
        "categorias": [
            "Metaphysics",
            "Ethics",
            "Politics",
            "Aesthetics"
        ],
        "nascimento": 1908,
        "morte": 1961
    },
    {
        "nome": "Plato",
        "categorias": [
            "Epistemology",
            "Metaphysics",
            "Ethics",
            "Politics"
        ],
        "nascimento": -427,
        "morte": -347
    },
    {
        "nome": "René_Descartes",
        "categorias": [
            "Epistemology",
            "Metaphysics",
            "Ethics",
            "Aesthetics"
        ],
        "nascimento": 1596,
        "morte": 1650
    },
    {
        "nome": "Gottfried_Wilhelm_Leibniz",
        "categorias": [
            "Epistemology",
            "Metaphysics",
            "Ethics",
            "Logic",
            "Politics"
        ],
        "nascimento": 1646,
        "morte": 1716
    },
    {
        "nome": "Nicolas_Malebranche",
        "categorias": [
            "Epistemology",
            "Metaphysics",
            "Ethics"
        ],
        "nascimento": 1638,
        "morte": 1715
    },
    {
        "nome": "Baruch_Spinoza",
        "categorias": [
            "Epistemology",
            "Metaphysics",
            "Ethics",
            "Logic",
            "Politics"
        ],
        "nascimento": 1632,
        "morte": 1677
    }
]